kraken_db_api/__init__.py
kraken_db_api/kraken_db_api.py
kraken_db_api/kraken_db_api_sqlite.py
kraken_db_api-0.0.2.dist-info/LICENSE.txt
kraken_db_api-0.0.2.dist-info/METADATA
kraken_db_api-0.0.2.dist-info/WHEEL
kraken_db_api-0.0.2.dist-info/top_level.txt
kraken_db_api-0.0.2.dist-info/RECORD
